embedding_disruptiveness/__init__.py
embedding_disruptiveness/datasets/__init__.py
embedding_disruptiveness/datasets/tripletdataset.py
embedding_disruptiveness/embedding/Embedding.py
embedding_disruptiveness/embedding/__init__.py
embedding_disruptiveness/loss/__init__.py
embedding_disruptiveness/loss/tripletloss.py
embedding_disruptiveness/models/__init__.py
embedding_disruptiveness/models/word2vec.py
embedding_disruptiveness/torch/__init__.py
embedding_disruptiveness/torch/train.py
embedding_disruptiveness/utils/__init__.py
embedding_disruptiveness/utils/disruption.py
embedding_disruptiveness/utils/node_sampler.py
embedding_disruptiveness/utils/random_walks.py
embedding_disruptiveness-1.0.0.dist-info/LICENSE
embedding_disruptiveness-1.0.0.dist-info/METADATA
embedding_disruptiveness-1.0.0.dist-info/WHEEL
embedding_disruptiveness-1.0.0.dist-info/top_level.txt
embedding_disruptiveness-1.0.0.dist-info/RECORD
