Metadata-Version: 2.1
Name: embedding-disruptiveness
Version: 1.0.0
Summary: A Python package to calculate the disruption index and embedding disruptiveness measure using a citation network.
Home-page: https://github.com/yourusername/embedding-disruptiveness
Author: Munjung Kim, Skojaku
Author-email: Munjung Kim <munjkim@iu.edu>, Skojaku <skojaku@binghamton.edu>
License: MIT
Project-URL: Homepage, https://github.com/MunjungKim/embedding-disruptiveness
Project-URL: Repository, https://github.com/MunjungKim/embedding-disruptiveness
Project-URL: Documentation, https://github.com/MunjungKim/embedding-disruptiveness#readme
Keywords: science of science,disruption index,citation,innovation,edm,embedding disruptiveness measure
Classifier: Programming Language :: Python :: 3
Classifier: License :: OSI Approved :: MIT License
Classifier: Operating System :: OS Independent
Requires-Python: >=3.8
License-File: LICENSE
Requires-Dist: tqdm
Requires-Dist: numpy
Requires-Dist: scikit-learn
Requires-Dist: torch
Requires-Dist: scipy
Requires-Dist: numba
Provides-Extra: tests
Requires-Dist: pytest; extra == "tests"
Requires-Dist: pytest-cov; extra == "tests"
